{"graph_0": {"_type": "graph", "edges": [], "nodes": [{"id": 140494306895968, "name": "conv_stem", "class_name": "Conv2dSame(3, 40, kernel_size=(3, 3), stride=(2, 2), bias=False)", "parameters": [["weight", [40, 3, 3, 3]]], "output_shape": [[256, 40, 32, 32]], "num_parameters": [1080]}, {"id": 140494306897312, "name": "bn1", "class_name": "BatchNorm2d(40, eps=0.001, momentum=0.1, affine=True, track_running_stats=True)", "parameters": [["weight", [40]], ["bias", [40]]], "output_shape": [[256, 40, 32, 32]], "num_parameters": [40, 40]}, {"id": 140494306894568, "name": "blocks.0.0", "class_name": "DepthwiseSeparableConv(\n  (conv_dw): Conv2d(40, 40, kernel_size=(3, 3), stride=(1, 1), padding=(1, 1), groups=40, bias=False)\n  (bn1): BatchNorm2d(40, eps=0.001, momentum=0.1, affine=True, track_running_stats=True)\n  (se): SqueezeExcite(\n    (conv_reduce): Conv2d(40, 10, kernel_size=(1, 1), stride=(1, 1))\n    (conv_expand): Conv2d(10, 40, kernel_size=(1, 1), stride=(1, 1))\n  )\n  (conv_pw): Conv2d(40, 24, kernel_size=(1, 1), stride=(1, 1), bias=False)\n  (bn2): BatchNorm2d(24, eps=0.001, momentum=0.1, affine=True, track_running_stats=True)\n)", "parameters": [["conv_dw.weight", [40, 1, 3, 3]], ["bn1.weight", [40]], ["bn1.bias", [40]], ["se.conv_reduce.weight", [10, 40, 1, 1]], ["se.conv_reduce.bias", [10]], ["se.conv_expand.weight", [40, 10, 1, 1]], ["se.conv_expand.bias", [40]], ["conv_pw.weight", [24, 40, 1, 1]], ["bn2.weight", [24]], ["bn2.bias", [24]]], "output_shape": [[256, 24, 32, 32]], "num_parameters": [360, 40, 40, 400, 10, 400, 40, 960, 24, 24]}, {"id": 140494306896528, "name": "blocks.0.1", "class_name": "DepthwiseSeparableConv(\n  (conv_dw): Conv2d(24, 24, kernel_size=(3, 3), stride=(1, 1), padding=(1, 1), groups=24, bias=False)\n  (bn1): BatchNorm2d(24, eps=0.001, momentum=0.1, affine=True, track_running_stats=True)\n  (se): SqueezeExcite(\n    (conv_reduce): Conv2d(24, 6, kernel_size=(1, 1), stride=(1, 1))\n    (conv_expand): Conv2d(6, 24, kernel_size=(1, 1), stride=(1, 1))\n  )\n  (conv_pw): Conv2d(24, 24, kernel_size=(1, 1), stride=(1, 1), bias=False)\n  (bn2): BatchNorm2d(24, eps=0.001, momentum=0.1, affine=True, track_running_stats=True)\n)", "parameters": [["conv_dw.weight", [24, 1, 3, 3]], ["bn1.weight", [24]], ["bn1.bias", [24]], ["se.conv_reduce.weight", [6, 24, 1, 1]], ["se.conv_reduce.bias", [6]], ["se.conv_expand.weight", [24, 6, 1, 1]], ["se.conv_expand.bias", [24]], ["conv_pw.weight", [24, 24, 1, 1]], ["bn2.weight", [24]], ["bn2.bias", [24]]], "output_shape": [[256, 24, 32, 32]], "num_parameters": [216, 24, 24, 144, 6, 144, 24, 576, 24, 24]}, {"id": 140494353814360, "name": "blocks.1.0", "class_name": "InvertedResidual(\n  (conv_pw): Conv2d(24, 144, kernel_size=(1, 1), stride=(1, 1), bias=False)\n  (bn1): BatchNorm2d(144, eps=0.001, momentum=0.1, affine=True, track_running_stats=True)\n  (conv_dw): Conv2dSame(144, 144, kernel_size=(3, 3), stride=(2, 2), groups=144, bias=False)\n  (bn2): BatchNorm2d(144, eps=0.001, momentum=0.1, affine=True, track_running_stats=True)\n  (se): SqueezeExcite(\n    (conv_reduce): Conv2d(144, 6, kernel_size=(1, 1), stride=(1, 1))\n    (conv_expand): Conv2d(6, 144, kernel_size=(1, 1), stride=(1, 1))\n  )\n  (conv_pwl): Conv2d(144, 32, kernel_size=(1, 1), stride=(1, 1), bias=False)\n  (bn3): BatchNorm2d(32, eps=0.001, momentum=0.1, affine=True, track_running_stats=True)\n)", "parameters": [["conv_pw.weight", [144, 24, 1, 1]], ["bn1.weight", [144]], ["bn1.bias", [144]], ["conv_dw.weight", [144, 1, 3, 3]], ["bn2.weight", [144]], ["bn2.bias", [144]], ["se.conv_reduce.weight", [6, 144, 1, 1]], ["se.conv_reduce.bias", [6]], ["se.conv_expand.weight", [144, 6, 1, 1]], ["se.conv_expand.bias", [144]], ["conv_pwl.weight", [32, 144, 1, 1]], ["bn3.weight", [32]], ["bn3.bias", [32]]], "output_shape": [[256, 32, 16, 16]], "num_parameters": [3456, 144, 144, 1296, 144, 144, 864, 6, 864, 144, 4608, 32, 32]}, {"id": 140494306829200, "name": "blocks.1.1", "class_name": "InvertedResidual(\n  (conv_pw): Conv2d(32, 192, kernel_size=(1, 1), stride=(1, 1), bias=False)\n  (bn1): BatchNorm2d(192, eps=0.001, momentum=0.1, affine=True, track_running_stats=True)\n  (conv_dw): Conv2d(192, 192, kernel_size=(3, 3), stride=(1, 1), padding=(1, 1), groups=192, bias=False)\n  (bn2): BatchNorm2d(192, eps=0.001, momentum=0.1, affine=True, track_running_stats=True)\n  (se): SqueezeExcite(\n    (conv_reduce): Conv2d(192, 8, kernel_size=(1, 1), stride=(1, 1))\n    (conv_expand): Conv2d(8, 192, kernel_size=(1, 1), stride=(1, 1))\n  )\n  (conv_pwl): Conv2d(192, 32, kernel_size=(1, 1), stride=(1, 1), bias=False)\n  (bn3): BatchNorm2d(32, eps=0.001, momentum=0.1, affine=True, track_running_stats=True)\n)", "parameters": [["conv_pw.weight", [192, 32, 1, 1]], ["bn1.weight", [192]], ["bn1.bias", [192]], ["conv_dw.weight", [192, 1, 3, 3]], ["bn2.weight", [192]], ["bn2.bias", [192]], ["se.conv_reduce.weight", [8, 192, 1, 1]], ["se.conv_reduce.bias", [8]], ["se.conv_expand.weight", [192, 8, 1, 1]], ["se.conv_expand.bias", [192]], ["conv_pwl.weight", [32, 192, 1, 1]], ["bn3.weight", [32]], ["bn3.bias", [32]]], "output_shape": [[256, 32, 16, 16]], "num_parameters": [6144, 192, 192, 1728, 192, 192, 1536, 8, 1536, 192, 6144, 32, 32]}, {"id": 140494306894624, "name": "blocks.1.2", "class_name": "InvertedResidual(\n  (conv_pw): Conv2d(32, 192, kernel_size=(1, 1), stride=(1, 1), bias=False)\n  (bn1): BatchNorm2d(192, eps=0.001, momentum=0.1, affine=True, track_running_stats=True)\n  (conv_dw): Conv2d(192, 192, kernel_size=(3, 3), stride=(1, 1), padding=(1, 1), groups=192, bias=False)\n  (bn2): BatchNorm2d(192, eps=0.001, momentum=0.1, affine=True, track_running_stats=True)\n  (se): SqueezeExcite(\n    (conv_reduce): Conv2d(192, 8, kernel_size=(1, 1), stride=(1, 1))\n    (conv_expand): Conv2d(8, 192, kernel_size=(1, 1), stride=(1, 1))\n  )\n  (conv_pwl): Conv2d(192, 32, kernel_size=(1, 1), stride=(1, 1), bias=False)\n  (bn3): BatchNorm2d(32, eps=0.001, momentum=0.1, affine=True, track_running_stats=True)\n)", "parameters": [["conv_pw.weight", [192, 32, 1, 1]], ["bn1.weight", [192]], ["bn1.bias", [192]], ["conv_dw.weight", [192, 1, 3, 3]], ["bn2.weight", [192]], ["bn2.bias", [192]], ["se.conv_reduce.weight", [8, 192, 1, 1]], ["se.conv_reduce.bias", [8]], ["se.conv_expand.weight", [192, 8, 1, 1]], ["se.conv_expand.bias", [192]], ["conv_pwl.weight", [32, 192, 1, 1]], ["bn3.weight", [32]], ["bn3.bias", [32]]], "output_shape": [[256, 32, 16, 16]], "num_parameters": [6144, 192, 192, 1728, 192, 192, 1536, 8, 1536, 192, 6144, 32, 32]}, {"id": 140496373062456, "name": "blocks.2.0", "class_name": "InvertedResidual(\n  (conv_pw): Conv2d(32, 192, kernel_size=(1, 1), stride=(1, 1), bias=False)\n  (bn1): BatchNorm2d(192, eps=0.001, momentum=0.1, affine=True, track_running_stats=True)\n  (conv_dw): Conv2dSame(192, 192, kernel_size=(5, 5), stride=(2, 2), groups=192, bias=False)\n  (bn2): BatchNorm2d(192, eps=0.001, momentum=0.1, affine=True, track_running_stats=True)\n  (se): SqueezeExcite(\n    (conv_reduce): Conv2d(192, 8, kernel_size=(1, 1), stride=(1, 1))\n    (conv_expand): Conv2d(8, 192, kernel_size=(1, 1), stride=(1, 1))\n  )\n  (conv_pwl): Conv2d(192, 48, kernel_size=(1, 1), stride=(1, 1), bias=False)\n  (bn3): BatchNorm2d(48, eps=0.001, momentum=0.1, affine=True, track_running_stats=True)\n)", "parameters": [["conv_pw.weight", [192, 32, 1, 1]], ["bn1.weight", [192]], ["bn1.bias", [192]], ["conv_dw.weight", [192, 1, 5, 5]], ["bn2.weight", [192]], ["bn2.bias", [192]], ["se.conv_reduce.weight", [8, 192, 1, 1]], ["se.conv_reduce.bias", [8]], ["se.conv_expand.weight", [192, 8, 1, 1]], ["se.conv_expand.bias", [192]], ["conv_pwl.weight", [48, 192, 1, 1]], ["bn3.weight", [48]], ["bn3.bias", [48]]], "output_shape": [[256, 48, 8, 8]], "num_parameters": [6144, 192, 192, 4800, 192, 192, 1536, 8, 1536, 192, 9216, 48, 48]}, {"id": 140494353436120, "name": "blocks.2.1", "class_name": "InvertedResidual(\n  (conv_pw): Conv2d(48, 288, kernel_size=(1, 1), stride=(1, 1), bias=False)\n  (bn1): BatchNorm2d(288, eps=0.001, momentum=0.1, affine=True, track_running_stats=True)\n  (conv_dw): Conv2d(288, 288, kernel_size=(5, 5), stride=(1, 1), padding=(2, 2), groups=288, bias=False)\n  (bn2): BatchNorm2d(288, eps=0.001, momentum=0.1, affine=True, track_running_stats=True)\n  (se): SqueezeExcite(\n    (conv_reduce): Conv2d(288, 12, kernel_size=(1, 1), stride=(1, 1))\n    (conv_expand): Conv2d(12, 288, kernel_size=(1, 1), stride=(1, 1))\n  )\n  (conv_pwl): Conv2d(288, 48, kernel_size=(1, 1), stride=(1, 1), bias=False)\n  (bn3): BatchNorm2d(48, eps=0.001, momentum=0.1, affine=True, track_running_stats=True)\n)", "parameters": [["conv_pw.weight", [288, 48, 1, 1]], ["bn1.weight", [288]], ["bn1.bias", [288]], ["conv_dw.weight", [288, 1, 5, 5]], ["bn2.weight", [288]], ["bn2.bias", [288]], ["se.conv_reduce.weight", [12, 288, 1, 1]], ["se.conv_reduce.bias", [12]], ["se.conv_expand.weight", [288, 12, 1, 1]], ["se.conv_expand.bias", [288]], ["conv_pwl.weight", [48, 288, 1, 1]], ["bn3.weight", [48]], ["bn3.bias", [48]]], "output_shape": [[256, 48, 8, 8]], "num_parameters": [13824, 288, 288, 7200, 288, 288, 3456, 12, 3456, 288, 13824, 48, 48]}, {"id": 140494353435952, "name": "blocks.2.2", "class_name": "InvertedResidual(\n  (conv_pw): Conv2d(48, 288, kernel_size=(1, 1), stride=(1, 1), bias=False)\n  (bn1): BatchNorm2d(288, eps=0.001, momentum=0.1, affine=True, track_running_stats=True)\n  (conv_dw): Conv2d(288, 288, kernel_size=(5, 5), stride=(1, 1), padding=(2, 2), groups=288, bias=False)\n  (bn2): BatchNorm2d(288, eps=0.001, momentum=0.1, affine=True, track_running_stats=True)\n  (se): SqueezeExcite(\n    (conv_reduce): Conv2d(288, 12, kernel_size=(1, 1), stride=(1, 1))\n    (conv_expand): Conv2d(12, 288, kernel_size=(1, 1), stride=(1, 1))\n  )\n  (conv_pwl): Conv2d(288, 48, kernel_size=(1, 1), stride=(1, 1), bias=False)\n  (bn3): BatchNorm2d(48, eps=0.001, momentum=0.1, affine=True, track_running_stats=True)\n)", "parameters": [["conv_pw.weight", [288, 48, 1, 1]], ["bn1.weight", [288]], ["bn1.bias", [288]], ["conv_dw.weight", [288, 1, 5, 5]], ["bn2.weight", [288]], ["bn2.bias", [288]], ["se.conv_reduce.weight", [12, 288, 1, 1]], ["se.conv_reduce.bias", [12]], ["se.conv_expand.weight", [288, 12, 1, 1]], ["se.conv_expand.bias", [288]], ["conv_pwl.weight", [48, 288, 1, 1]], ["bn3.weight", [48]], ["bn3.bias", [48]]], "output_shape": [[256, 48, 8, 8]], "num_parameters": [13824, 288, 288, 7200, 288, 288, 3456, 12, 3456, 288, 13824, 48, 48]}, {"id": 140494306854672, "name": "blocks.3.0", "class_name": "InvertedResidual(\n  (conv_pw): Conv2d(48, 288, kernel_size=(1, 1), stride=(1, 1), bias=False)\n  (bn1): BatchNorm2d(288, eps=0.001, momentum=0.1, affine=True, track_running_stats=True)\n  (conv_dw): Conv2dSame(288, 288, kernel_size=(3, 3), stride=(2, 2), groups=288, bias=False)\n  (bn2): BatchNorm2d(288, eps=0.001, momentum=0.1, affine=True, track_running_stats=True)\n  (se): SqueezeExcite(\n    (conv_reduce): Conv2d(288, 12, kernel_size=(1, 1), stride=(1, 1))\n    (conv_expand): Conv2d(12, 288, kernel_size=(1, 1), stride=(1, 1))\n  )\n  (conv_pwl): Conv2d(288, 96, kernel_size=(1, 1), stride=(1, 1), bias=False)\n  (bn3): BatchNorm2d(96, eps=0.001, momentum=0.1, affine=True, track_running_stats=True)\n)", "parameters": [["conv_pw.weight", [288, 48, 1, 1]], ["bn1.weight", [288]], ["bn1.bias", [288]], ["conv_dw.weight", [288, 1, 3, 3]], ["bn2.weight", [288]], ["bn2.bias", [288]], ["se.conv_reduce.weight", [12, 288, 1, 1]], ["se.conv_reduce.bias", [12]], ["se.conv_expand.weight", [288, 12, 1, 1]], ["se.conv_expand.bias", [288]], ["conv_pwl.weight", [96, 288, 1, 1]], ["bn3.weight", [96]], ["bn3.bias", [96]]], "output_shape": [[256, 96, 4, 4]], "num_parameters": [13824, 288, 288, 2592, 288, 288, 3456, 12, 3456, 288, 27648, 96, 96]}, {"id": 140494306854224, "name": "blocks.3.1", "class_name": "InvertedResidual(\n  (conv_pw): Conv2d(96, 576, kernel_size=(1, 1), stride=(1, 1), bias=False)\n  (bn1): BatchNorm2d(576, eps=0.001, momentum=0.1, affine=True, track_running_stats=True)\n  (conv_dw): Conv2d(576, 576, kernel_size=(3, 3), stride=(1, 1), padding=(1, 1), groups=576, bias=False)\n  (bn2): BatchNorm2d(576, eps=0.001, momentum=0.1, affine=True, track_running_stats=True)\n  (se): SqueezeExcite(\n    (conv_reduce): Conv2d(576, 24, kernel_size=(1, 1), stride=(1, 1))\n    (conv_expand): Conv2d(24, 576, kernel_size=(1, 1), stride=(1, 1))\n  )\n  (conv_pwl): Conv2d(576, 96, kernel_size=(1, 1), stride=(1, 1), bias=False)\n  (bn3): BatchNorm2d(96, eps=0.001, momentum=0.1, affine=True, track_running_stats=True)\n)", "parameters": [["conv_pw.weight", [576, 96, 1, 1]], ["bn1.weight", [576]], ["bn1.bias", [576]], ["conv_dw.weight", [576, 1, 3, 3]], ["bn2.weight", [576]], ["bn2.bias", [576]], ["se.conv_reduce.weight", [24, 576, 1, 1]], ["se.conv_reduce.bias", [24]], ["se.conv_expand.weight", [576, 24, 1, 1]], ["se.conv_expand.bias", [576]], ["conv_pwl.weight", [96, 576, 1, 1]], ["bn3.weight", [96]], ["bn3.bias", [96]]], "output_shape": [[256, 96, 4, 4]], "num_parameters": [55296, 576, 576, 5184, 576, 576, 13824, 24, 13824, 576, 55296, 96, 96]}, {"id": 140494306856464, "name": "blocks.3.2", "class_name": "InvertedResidual(\n  (conv_pw): Conv2d(96, 576, kernel_size=(1, 1), stride=(1, 1), bias=False)\n  (bn1): BatchNorm2d(576, eps=0.001, momentum=0.1, affine=True, track_running_stats=True)\n  (conv_dw): Conv2d(576, 576, kernel_size=(3, 3), stride=(1, 1), padding=(1, 1), groups=576, bias=False)\n  (bn2): BatchNorm2d(576, eps=0.001, momentum=0.1, affine=True, track_running_stats=True)\n  (se): SqueezeExcite(\n    (conv_reduce): Conv2d(576, 24, kernel_size=(1, 1), stride=(1, 1))\n    (conv_expand): Conv2d(24, 576, kernel_size=(1, 1), stride=(1, 1))\n  )\n  (conv_pwl): Conv2d(576, 96, kernel_size=(1, 1), stride=(1, 1), bias=False)\n  (bn3): BatchNorm2d(96, eps=0.001, momentum=0.1, affine=True, track_running_stats=True)\n)", "parameters": [["conv_pw.weight", [576, 96, 1, 1]], ["bn1.weight", [576]], ["bn1.bias", [576]], ["conv_dw.weight", [576, 1, 3, 3]], ["bn2.weight", [576]], ["bn2.bias", [576]], ["se.conv_reduce.weight", [24, 576, 1, 1]], ["se.conv_reduce.bias", [24]], ["se.conv_expand.weight", [576, 24, 1, 1]], ["se.conv_expand.bias", [576]], ["conv_pwl.weight", [96, 576, 1, 1]], ["bn3.weight", [96]], ["bn3.bias", [96]]], "output_shape": [[256, 96, 4, 4]], "num_parameters": [55296, 576, 576, 5184, 576, 576, 13824, 24, 13824, 576, 55296, 96, 96]}, {"id": 140494306853944, "name": "blocks.3.3", "class_name": "InvertedResidual(\n  (conv_pw): Conv2d(96, 576, kernel_size=(1, 1), stride=(1, 1), bias=False)\n  (bn1): BatchNorm2d(576, eps=0.001, momentum=0.1, affine=True, track_running_stats=True)\n  (conv_dw): Conv2d(576, 576, kernel_size=(3, 3), stride=(1, 1), padding=(1, 1), groups=576, bias=False)\n  (bn2): BatchNorm2d(576, eps=0.001, momentum=0.1, affine=True, track_running_stats=True)\n  (se): SqueezeExcite(\n    (conv_reduce): Conv2d(576, 24, kernel_size=(1, 1), stride=(1, 1))\n    (conv_expand): Conv2d(24, 576, kernel_size=(1, 1), stride=(1, 1))\n  )\n  (conv_pwl): Conv2d(576, 96, kernel_size=(1, 1), stride=(1, 1), bias=False)\n  (bn3): BatchNorm2d(96, eps=0.001, momentum=0.1, affine=True, track_running_stats=True)\n)", "parameters": [["conv_pw.weight", [576, 96, 1, 1]], ["bn1.weight", [576]], ["bn1.bias", [576]], ["conv_dw.weight", [576, 1, 3, 3]], ["bn2.weight", [576]], ["bn2.bias", [576]], ["se.conv_reduce.weight", [24, 576, 1, 1]], ["se.conv_reduce.bias", [24]], ["se.conv_expand.weight", [576, 24, 1, 1]], ["se.conv_expand.bias", [576]], ["conv_pwl.weight", [96, 576, 1, 1]], ["bn3.weight", [96]], ["bn3.bias", [96]]], "output_shape": [[256, 96, 4, 4]], "num_parameters": [55296, 576, 576, 5184, 576, 576, 13824, 24, 13824, 576, 55296, 96, 96]}, {"id": 140494306854448, "name": "blocks.3.4", "class_name": "InvertedResidual(\n  (conv_pw): Conv2d(96, 576, kernel_size=(1, 1), stride=(1, 1), bias=False)\n  (bn1): BatchNorm2d(576, eps=0.001, momentum=0.1, affine=True, track_running_stats=True)\n  (conv_dw): Conv2d(576, 576, kernel_size=(3, 3), stride=(1, 1), padding=(1, 1), groups=576, bias=False)\n  (bn2): BatchNorm2d(576, eps=0.001, momentum=0.1, affine=True, track_running_stats=True)\n  (se): SqueezeExcite(\n    (conv_reduce): Conv2d(576, 24, kernel_size=(1, 1), stride=(1, 1))\n    (conv_expand): Conv2d(24, 576, kernel_size=(1, 1), stride=(1, 1))\n  )\n  (conv_pwl): Conv2d(576, 96, kernel_size=(1, 1), stride=(1, 1), bias=False)\n  (bn3): BatchNorm2d(96, eps=0.001, momentum=0.1, affine=True, track_running_stats=True)\n)", "parameters": [["conv_pw.weight", [576, 96, 1, 1]], ["bn1.weight", [576]], ["bn1.bias", [576]], ["conv_dw.weight", [576, 1, 3, 3]], ["bn2.weight", [576]], ["bn2.bias", [576]], ["se.conv_reduce.weight", [24, 576, 1, 1]], ["se.conv_reduce.bias", [24]], ["se.conv_expand.weight", [576, 24, 1, 1]], ["se.conv_expand.bias", [576]], ["conv_pwl.weight", [96, 576, 1, 1]], ["bn3.weight", [96]], ["bn3.bias", [96]]], "output_shape": [[256, 96, 4, 4]], "num_parameters": [55296, 576, 576, 5184, 576, 576, 13824, 24, 13824, 576, 55296, 96, 96]}, {"id": 140494306853776, "name": "blocks.4.0", "class_name": "InvertedResidual(\n  (conv_pw): Conv2d(96, 576, kernel_size=(1, 1), stride=(1, 1), bias=False)\n  (bn1): BatchNorm2d(576, eps=0.001, momentum=0.1, affine=True, track_running_stats=True)\n  (conv_dw): Conv2d(576, 576, kernel_size=(5, 5), stride=(1, 1), padding=(2, 2), groups=576, bias=False)\n  (bn2): BatchNorm2d(576, eps=0.001, momentum=0.1, affine=True, track_running_stats=True)\n  (se): SqueezeExcite(\n    (conv_reduce): Conv2d(576, 24, kernel_size=(1, 1), stride=(1, 1))\n    (conv_expand): Conv2d(24, 576, kernel_size=(1, 1), stride=(1, 1))\n  )\n  (conv_pwl): Conv2d(576, 136, kernel_size=(1, 1), stride=(1, 1), bias=False)\n  (bn3): BatchNorm2d(136, eps=0.001, momentum=0.1, affine=True, track_running_stats=True)\n)", "parameters": [["conv_pw.weight", [576, 96, 1, 1]], ["bn1.weight", [576]], ["bn1.bias", [576]], ["conv_dw.weight", [576, 1, 5, 5]], ["bn2.weight", [576]], ["bn2.bias", [576]], ["se.conv_reduce.weight", [24, 576, 1, 1]], ["se.conv_reduce.bias", [24]], ["se.conv_expand.weight", [576, 24, 1, 1]], ["se.conv_expand.bias", [576]], ["conv_pwl.weight", [136, 576, 1, 1]], ["bn3.weight", [136]], ["bn3.bias", [136]]], "output_shape": [[256, 136, 4, 4]], "num_parameters": [55296, 576, 576, 14400, 576, 576, 13824, 24, 13824, 576, 78336, 136, 136]}, {"id": 140494314877392, "name": "blocks.4.1", "class_name": "InvertedResidual(\n  (conv_pw): Conv2d(136, 816, kernel_size=(1, 1), stride=(1, 1), bias=False)\n  (bn1): BatchNorm2d(816, eps=0.001, momentum=0.1, affine=True, track_running_stats=True)\n  (conv_dw): Conv2d(816, 816, kernel_size=(5, 5), stride=(1, 1), padding=(2, 2), groups=816, bias=False)\n  (bn2): BatchNorm2d(816, eps=0.001, momentum=0.1, affine=True, track_running_stats=True)\n  (se): SqueezeExcite(\n    (conv_reduce): Conv2d(816, 34, kernel_size=(1, 1), stride=(1, 1))\n    (conv_expand): Conv2d(34, 816, kernel_size=(1, 1), stride=(1, 1))\n  )\n  (conv_pwl): Conv2d(816, 136, kernel_size=(1, 1), stride=(1, 1), bias=False)\n  (bn3): BatchNorm2d(136, eps=0.001, momentum=0.1, affine=True, track_running_stats=True)\n)", "parameters": [["conv_pw.weight", [816, 136, 1, 1]], ["bn1.weight", [816]], ["bn1.bias", [816]], ["conv_dw.weight", [816, 1, 5, 5]], ["bn2.weight", [816]], ["bn2.bias", [816]], ["se.conv_reduce.weight", [34, 816, 1, 1]], ["se.conv_reduce.bias", [34]], ["se.conv_expand.weight", [816, 34, 1, 1]], ["se.conv_expand.bias", [816]], ["conv_pwl.weight", [136, 816, 1, 1]], ["bn3.weight", [136]], ["bn3.bias", [136]]], "output_shape": [[256, 136, 4, 4]], "num_parameters": [110976, 816, 816, 20400, 816, 816, 27744, 34, 27744, 816, 110976, 136, 136]}, {"id": 140494314877952, "name": "blocks.4.2", "class_name": "InvertedResidual(\n  (conv_pw): Conv2d(136, 816, kernel_size=(1, 1), stride=(1, 1), bias=False)\n  (bn1): BatchNorm2d(816, eps=0.001, momentum=0.1, affine=True, track_running_stats=True)\n  (conv_dw): Conv2d(816, 816, kernel_size=(5, 5), stride=(1, 1), padding=(2, 2), groups=816, bias=False)\n  (bn2): BatchNorm2d(816, eps=0.001, momentum=0.1, affine=True, track_running_stats=True)\n  (se): SqueezeExcite(\n    (conv_reduce): Conv2d(816, 34, kernel_size=(1, 1), stride=(1, 1))\n    (conv_expand): Conv2d(34, 816, kernel_size=(1, 1), stride=(1, 1))\n  )\n  (conv_pwl): Conv2d(816, 136, kernel_size=(1, 1), stride=(1, 1), bias=False)\n  (bn3): BatchNorm2d(136, eps=0.001, momentum=0.1, affine=True, track_running_stats=True)\n)", "parameters": [["conv_pw.weight", [816, 136, 1, 1]], ["bn1.weight", [816]], ["bn1.bias", [816]], ["conv_dw.weight", [816, 1, 5, 5]], ["bn2.weight", [816]], ["bn2.bias", [816]], ["se.conv_reduce.weight", [34, 816, 1, 1]], ["se.conv_reduce.bias", [34]], ["se.conv_expand.weight", [816, 34, 1, 1]], ["se.conv_expand.bias", [816]], ["conv_pwl.weight", [136, 816, 1, 1]], ["bn3.weight", [136]], ["bn3.bias", [136]]], "output_shape": [[256, 136, 4, 4]], "num_parameters": [110976, 816, 816, 20400, 816, 816, 27744, 34, 27744, 816, 110976, 136, 136]}, {"id": 140494314878512, "name": "blocks.4.3", "class_name": "InvertedResidual(\n  (conv_pw): Conv2d(136, 816, kernel_size=(1, 1), stride=(1, 1), bias=False)\n  (bn1): BatchNorm2d(816, eps=0.001, momentum=0.1, affine=True, track_running_stats=True)\n  (conv_dw): Conv2d(816, 816, kernel_size=(5, 5), stride=(1, 1), padding=(2, 2), groups=816, bias=False)\n  (bn2): BatchNorm2d(816, eps=0.001, momentum=0.1, affine=True, track_running_stats=True)\n  (se): SqueezeExcite(\n    (conv_reduce): Conv2d(816, 34, kernel_size=(1, 1), stride=(1, 1))\n    (conv_expand): Conv2d(34, 816, kernel_size=(1, 1), stride=(1, 1))\n  )\n  (conv_pwl): Conv2d(816, 136, kernel_size=(1, 1), stride=(1, 1), bias=False)\n  (bn3): BatchNorm2d(136, eps=0.001, momentum=0.1, affine=True, track_running_stats=True)\n)", "parameters": [["conv_pw.weight", [816, 136, 1, 1]], ["bn1.weight", [816]], ["bn1.bias", [816]], ["conv_dw.weight", [816, 1, 5, 5]], ["bn2.weight", [816]], ["bn2.bias", [816]], ["se.conv_reduce.weight", [34, 816, 1, 1]], ["se.conv_reduce.bias", [34]], ["se.conv_expand.weight", [816, 34, 1, 1]], ["se.conv_expand.bias", [816]], ["conv_pwl.weight", [136, 816, 1, 1]], ["bn3.weight", [136]], ["bn3.bias", [136]]], "output_shape": [[256, 136, 4, 4]], "num_parameters": [110976, 816, 816, 20400, 816, 816, 27744, 34, 27744, 816, 110976, 136, 136]}, {"id": 140494314879072, "name": "blocks.4.4", "class_name": "InvertedResidual(\n  (conv_pw): Conv2d(136, 816, kernel_size=(1, 1), stride=(1, 1), bias=False)\n  (bn1): BatchNorm2d(816, eps=0.001, momentum=0.1, affine=True, track_running_stats=True)\n  (conv_dw): Conv2d(816, 816, kernel_size=(5, 5), stride=(1, 1), padding=(2, 2), groups=816, bias=False)\n  (bn2): BatchNorm2d(816, eps=0.001, momentum=0.1, affine=True, track_running_stats=True)\n  (se): SqueezeExcite(\n    (conv_reduce): Conv2d(816, 34, kernel_size=(1, 1), stride=(1, 1))\n    (conv_expand): Conv2d(34, 816, kernel_size=(1, 1), stride=(1, 1))\n  )\n  (conv_pwl): Conv2d(816, 136, kernel_size=(1, 1), stride=(1, 1), bias=False)\n  (bn3): BatchNorm2d(136, eps=0.001, momentum=0.1, affine=True, track_running_stats=True)\n)", "parameters": [["conv_pw.weight", [816, 136, 1, 1]], ["bn1.weight", [816]], ["bn1.bias", [816]], ["conv_dw.weight", [816, 1, 5, 5]], ["bn2.weight", [816]], ["bn2.bias", [816]], ["se.conv_reduce.weight", [34, 816, 1, 1]], ["se.conv_reduce.bias", [34]], ["se.conv_expand.weight", [816, 34, 1, 1]], ["se.conv_expand.bias", [816]], ["conv_pwl.weight", [136, 816, 1, 1]], ["bn3.weight", [136]], ["bn3.bias", [136]]], "output_shape": [[256, 136, 4, 4]], "num_parameters": [110976, 816, 816, 20400, 816, 816, 27744, 34, 27744, 816, 110976, 136, 136]}, {"id": 140494314879912, "name": "blocks.5.0", "class_name": "InvertedResidual(\n  (conv_pw): Conv2d(136, 816, kernel_size=(1, 1), stride=(1, 1), bias=False)\n  (bn1): BatchNorm2d(816, eps=0.001, momentum=0.1, affine=True, track_running_stats=True)\n  (conv_dw): Conv2dSame(816, 816, kernel_size=(5, 5), stride=(2, 2), groups=816, bias=False)\n  (bn2): BatchNorm2d(816, eps=0.001, momentum=0.1, affine=True, track_running_stats=True)\n  (se): SqueezeExcite(\n    (conv_reduce): Conv2d(816, 34, kernel_size=(1, 1), stride=(1, 1))\n    (conv_expand): Conv2d(34, 816, kernel_size=(1, 1), stride=(1, 1))\n  )\n  (conv_pwl): Conv2d(816, 232, kernel_size=(1, 1), stride=(1, 1), bias=False)\n  (bn3): BatchNorm2d(232, eps=0.001, momentum=0.1, affine=True, track_running_stats=True)\n)", "parameters": [["conv_pw.weight", [816, 136, 1, 1]], ["bn1.weight", [816]], ["bn1.bias", [816]], ["conv_dw.weight", [816, 1, 5, 5]], ["bn2.weight", [816]], ["bn2.bias", [816]], ["se.conv_reduce.weight", [34, 816, 1, 1]], ["se.conv_reduce.bias", [34]], ["se.conv_expand.weight", [816, 34, 1, 1]], ["se.conv_expand.bias", [816]], ["conv_pwl.weight", [232, 816, 1, 1]], ["bn3.weight", [232]], ["bn3.bias", [232]]], "output_shape": [[256, 232, 2, 2]], "num_parameters": [110976, 816, 816, 20400, 816, 816, 27744, 34, 27744, 816, 189312, 232, 232]}, {"id": 140494314880472, "name": "blocks.5.1", "class_name": "InvertedResidual(\n  (conv_pw): Conv2d(232, 1392, kernel_size=(1, 1), stride=(1, 1), bias=False)\n  (bn1): BatchNorm2d(1392, eps=0.001, momentum=0.1, affine=True, track_running_stats=True)\n  (conv_dw): Conv2d(1392, 1392, kernel_size=(5, 5), stride=(1, 1), padding=(2, 2), groups=1392, bias=False)\n  (bn2): BatchNorm2d(1392, eps=0.001, momentum=0.1, affine=True, track_running_stats=True)\n  (se): SqueezeExcite(\n    (conv_reduce): Conv2d(1392, 58, kernel_size=(1, 1), stride=(1, 1))\n    (conv_expand): Conv2d(58, 1392, kernel_size=(1, 1), stride=(1, 1))\n  )\n  (conv_pwl): Conv2d(1392, 232, kernel_size=(1, 1), stride=(1, 1), bias=False)\n  (bn3): BatchNorm2d(232, eps=0.001, momentum=0.1, affine=True, track_running_stats=True)\n)", "parameters": [["conv_pw.weight", [1392, 232, 1, 1]], ["bn1.weight", [1392]], ["bn1.bias", [1392]], ["conv_dw.weight", [1392, 1, 5, 5]], ["bn2.weight", [1392]], ["bn2.bias", [1392]], ["se.conv_reduce.weight", [58, 1392, 1, 1]], ["se.conv_reduce.bias", [58]], ["se.conv_expand.weight", [1392, 58, 1, 1]], ["se.conv_expand.bias", [1392]], ["conv_pwl.weight", [232, 1392, 1, 1]], ["bn3.weight", [232]], ["bn3.bias", [232]]], "output_shape": [[256, 232, 2, 2]], "num_parameters": [322944, 1392, 1392, 34800, 1392, 1392, 80736, 58, 80736, 1392, 322944, 232, 232]}, {"id": 140494314573896, "name": "blocks.5.2", "class_name": "InvertedResidual(\n  (conv_pw): Conv2d(232, 1392, kernel_size=(1, 1), stride=(1, 1), bias=False)\n  (bn1): BatchNorm2d(1392, eps=0.001, momentum=0.1, affine=True, track_running_stats=True)\n  (conv_dw): Conv2d(1392, 1392, kernel_size=(5, 5), stride=(1, 1), padding=(2, 2), groups=1392, bias=False)\n  (bn2): BatchNorm2d(1392, eps=0.001, momentum=0.1, affine=True, track_running_stats=True)\n  (se): SqueezeExcite(\n    (conv_reduce): Conv2d(1392, 58, kernel_size=(1, 1), stride=(1, 1))\n    (conv_expand): Conv2d(58, 1392, kernel_size=(1, 1), stride=(1, 1))\n  )\n  (conv_pwl): Conv2d(1392, 232, kernel_size=(1, 1), stride=(1, 1), bias=False)\n  (bn3): BatchNorm2d(232, eps=0.001, momentum=0.1, affine=True, track_running_stats=True)\n)", "parameters": [["conv_pw.weight", [1392, 232, 1, 1]], ["bn1.weight", [1392]], ["bn1.bias", [1392]], ["conv_dw.weight", [1392, 1, 5, 5]], ["bn2.weight", [1392]], ["bn2.bias", [1392]], ["se.conv_reduce.weight", [58, 1392, 1, 1]], ["se.conv_reduce.bias", [58]], ["se.conv_expand.weight", [1392, 58, 1, 1]], ["se.conv_expand.bias", [1392]], ["conv_pwl.weight", [232, 1392, 1, 1]], ["bn3.weight", [232]], ["bn3.bias", [232]]], "output_shape": [[256, 232, 2, 2]], "num_parameters": [322944, 1392, 1392, 34800, 1392, 1392, 80736, 58, 80736, 1392, 322944, 232, 232]}, {"id": 140494314574456, "name": "blocks.5.3", "class_name": "InvertedResidual(\n  (conv_pw): Conv2d(232, 1392, kernel_size=(1, 1), stride=(1, 1), bias=False)\n  (bn1): BatchNorm2d(1392, eps=0.001, momentum=0.1, affine=True, track_running_stats=True)\n  (conv_dw): Conv2d(1392, 1392, kernel_size=(5, 5), stride=(1, 1), padding=(2, 2), groups=1392, bias=False)\n  (bn2): BatchNorm2d(1392, eps=0.001, momentum=0.1, affine=True, track_running_stats=True)\n  (se): SqueezeExcite(\n    (conv_reduce): Conv2d(1392, 58, kernel_size=(1, 1), stride=(1, 1))\n    (conv_expand): Conv2d(58, 1392, kernel_size=(1, 1), stride=(1, 1))\n  )\n  (conv_pwl): Conv2d(1392, 232, kernel_size=(1, 1), stride=(1, 1), bias=False)\n  (bn3): BatchNorm2d(232, eps=0.001, momentum=0.1, affine=True, track_running_stats=True)\n)", "parameters": [["conv_pw.weight", [1392, 232, 1, 1]], ["bn1.weight", [1392]], ["bn1.bias", [1392]], ["conv_dw.weight", [1392, 1, 5, 5]], ["bn2.weight", [1392]], ["bn2.bias", [1392]], ["se.conv_reduce.weight", [58, 1392, 1, 1]], ["se.conv_reduce.bias", [58]], ["se.conv_expand.weight", [1392, 58, 1, 1]], ["se.conv_expand.bias", [1392]], ["conv_pwl.weight", [232, 1392, 1, 1]], ["bn3.weight", [232]], ["bn3.bias", [232]]], "output_shape": [[256, 232, 2, 2]], "num_parameters": [322944, 1392, 1392, 34800, 1392, 1392, 80736, 58, 80736, 1392, 322944, 232, 232]}, {"id": 140494314575016, "name": "blocks.5.4", "class_name": "InvertedResidual(\n  (conv_pw): Conv2d(232, 1392, kernel_size=(1, 1), stride=(1, 1), bias=False)\n  (bn1): BatchNorm2d(1392, eps=0.001, momentum=0.1, affine=True, track_running_stats=True)\n  (conv_dw): Conv2d(1392, 1392, kernel_size=(5, 5), stride=(1, 1), padding=(2, 2), groups=1392, bias=False)\n  (bn2): BatchNorm2d(1392, eps=0.001, momentum=0.1, affine=True, track_running_stats=True)\n  (se): SqueezeExcite(\n    (conv_reduce): Conv2d(1392, 58, kernel_size=(1, 1), stride=(1, 1))\n    (conv_expand): Conv2d(58, 1392, kernel_size=(1, 1), stride=(1, 1))\n  )\n  (conv_pwl): Conv2d(1392, 232, kernel_size=(1, 1), stride=(1, 1), bias=False)\n  (bn3): BatchNorm2d(232, eps=0.001, momentum=0.1, affine=True, track_running_stats=True)\n)", "parameters": [["conv_pw.weight", [1392, 232, 1, 1]], ["bn1.weight", [1392]], ["bn1.bias", [1392]], ["conv_dw.weight", [1392, 1, 5, 5]], ["bn2.weight", [1392]], ["bn2.bias", [1392]], ["se.conv_reduce.weight", [58, 1392, 1, 1]], ["se.conv_reduce.bias", [58]], ["se.conv_expand.weight", [1392, 58, 1, 1]], ["se.conv_expand.bias", [1392]], ["conv_pwl.weight", [232, 1392, 1, 1]], ["bn3.weight", [232]], ["bn3.bias", [232]]], "output_shape": [[256, 232, 2, 2]], "num_parameters": [322944, 1392, 1392, 34800, 1392, 1392, 80736, 58, 80736, 1392, 322944, 232, 232]}, {"id": 140494314575576, "name": "blocks.5.5", "class_name": "InvertedResidual(\n  (conv_pw): Conv2d(232, 1392, kernel_size=(1, 1), stride=(1, 1), bias=False)\n  (bn1): BatchNorm2d(1392, eps=0.001, momentum=0.1, affine=True, track_running_stats=True)\n  (conv_dw): Conv2d(1392, 1392, kernel_size=(5, 5), stride=(1, 1), padding=(2, 2), groups=1392, bias=False)\n  (bn2): BatchNorm2d(1392, eps=0.001, momentum=0.1, affine=True, track_running_stats=True)\n  (se): SqueezeExcite(\n    (conv_reduce): Conv2d(1392, 58, kernel_size=(1, 1), stride=(1, 1))\n    (conv_expand): Conv2d(58, 1392, kernel_size=(1, 1), stride=(1, 1))\n  )\n  (conv_pwl): Conv2d(1392, 232, kernel_size=(1, 1), stride=(1, 1), bias=False)\n  (bn3): BatchNorm2d(232, eps=0.001, momentum=0.1, affine=True, track_running_stats=True)\n)", "parameters": [["conv_pw.weight", [1392, 232, 1, 1]], ["bn1.weight", [1392]], ["bn1.bias", [1392]], ["conv_dw.weight", [1392, 1, 5, 5]], ["bn2.weight", [1392]], ["bn2.bias", [1392]], ["se.conv_reduce.weight", [58, 1392, 1, 1]], ["se.conv_reduce.bias", [58]], ["se.conv_expand.weight", [1392, 58, 1, 1]], ["se.conv_expand.bias", [1392]], ["conv_pwl.weight", [232, 1392, 1, 1]], ["bn3.weight", [232]], ["bn3.bias", [232]]], "output_shape": [[256, 232, 2, 2]], "num_parameters": [322944, 1392, 1392, 34800, 1392, 1392, 80736, 58, 80736, 1392, 322944, 232, 232]}, {"id": 140494314576136, "name": "blocks.6.0", "class_name": "InvertedResidual(\n  (conv_pw): Conv2d(232, 1392, kernel_size=(1, 1), stride=(1, 1), bias=False)\n  (bn1): BatchNorm2d(1392, eps=0.001, momentum=0.1, affine=True, track_running_stats=True)\n  (conv_dw): Conv2d(1392, 1392, kernel_size=(3, 3), stride=(1, 1), padding=(1, 1), groups=1392, bias=False)\n  (bn2): BatchNorm2d(1392, eps=0.001, momentum=0.1, affine=True, track_running_stats=True)\n  (se): SqueezeExcite(\n    (conv_reduce): Conv2d(1392, 58, kernel_size=(1, 1), stride=(1, 1))\n    (conv_expand): Conv2d(58, 1392, kernel_size=(1, 1), stride=(1, 1))\n  )\n  (conv_pwl): Conv2d(1392, 384, kernel_size=(1, 1), stride=(1, 1), bias=False)\n  (bn3): BatchNorm2d(384, eps=0.001, momentum=0.1, affine=True, track_running_stats=True)\n)", "parameters": [["conv_pw.weight", [1392, 232, 1, 1]], ["bn1.weight", [1392]], ["bn1.bias", [1392]], ["conv_dw.weight", [1392, 1, 3, 3]], ["bn2.weight", [1392]], ["bn2.bias", [1392]], ["se.conv_reduce.weight", [58, 1392, 1, 1]], ["se.conv_reduce.bias", [58]], ["se.conv_expand.weight", [1392, 58, 1, 1]], ["se.conv_expand.bias", [1392]], ["conv_pwl.weight", [384, 1392, 1, 1]], ["bn3.weight", [384]], ["bn3.bias", [384]]], "output_shape": [[256, 384, 2, 2]], "num_parameters": [322944, 1392, 1392, 12528, 1392, 1392, 80736, 58, 80736, 1392, 534528, 384, 384]}, {"id": 140494314577032, "name": "blocks.6.1", "class_name": "InvertedResidual(\n  (conv_pw): Conv2d(384, 2304, kernel_size=(1, 1), stride=(1, 1), bias=False)\n  (bn1): BatchNorm2d(2304, eps=0.001, momentum=0.1, affine=True, track_running_stats=True)\n  (conv_dw): Conv2d(2304, 2304, kernel_size=(3, 3), stride=(1, 1), padding=(1, 1), groups=2304, bias=False)\n  (bn2): BatchNorm2d(2304, eps=0.001, momentum=0.1, affine=True, track_running_stats=True)\n  (se): SqueezeExcite(\n    (conv_reduce): Conv2d(2304, 96, kernel_size=(1, 1), stride=(1, 1))\n    (conv_expand): Conv2d(96, 2304, kernel_size=(1, 1), stride=(1, 1))\n  )\n  (conv_pwl): Conv2d(2304, 384, kernel_size=(1, 1), stride=(1, 1), bias=False)\n  (bn3): BatchNorm2d(384, eps=0.001, momentum=0.1, affine=True, track_running_stats=True)\n)", "parameters": [["conv_pw.weight", [2304, 384, 1, 1]], ["bn1.weight", [2304]], ["bn1.bias", [2304]], ["conv_dw.weight", [2304, 1, 3, 3]], ["bn2.weight", [2304]], ["bn2.bias", [2304]], ["se.conv_reduce.weight", [96, 2304, 1, 1]], ["se.conv_reduce.bias", [96]], ["se.conv_expand.weight", [2304, 96, 1, 1]], ["se.conv_expand.bias", [2304]], ["conv_pwl.weight", [384, 2304, 1, 1]], ["bn3.weight", [384]], ["bn3.bias", [384]]], "output_shape": [[256, 384, 2, 2]], "num_parameters": [884736, 2304, 2304, 20736, 2304, 2304, 221184, 96, 221184, 2304, 884736, 384, 384]}, {"id": 140494306897872, "name": "conv_head", "class_name": "Conv2d(384, 1536, kernel_size=(1, 1), stride=(1, 1), bias=False)", "parameters": [["weight", [1536, 384, 1, 1]]], "output_shape": [[256, 1536, 2, 2]], "num_parameters": [589824]}, {"id": 140494314258672, "name": "bn2", "class_name": "BatchNorm2d(1536, eps=0.001, momentum=0.1, affine=True, track_running_stats=True)", "parameters": [["weight", [1536]], ["bias", [1536]]], "output_shape": [[256, 1536, 2, 2]], "num_parameters": [1536, 1536]}, {"id": 140494314258728, "name": "global_pool", "class_name": "SelectAdaptivePool2d (output_size=1, pool_type=avg)", "parameters": [], "output_shape": [[256, 1536, 1, 1]], "num_parameters": []}, {"id": 140494314258840, "name": "classifier", "class_name": "Linear(in_features=1536, out_features=4, bias=True)", "parameters": [["weight", [4, 1536]], ["bias", [4]]], "output_shape": [[256, 4]], "num_parameters": [6144, 4]}], "format": "torch"}, "_runtime": 798.9134776592255, "_timestamp": 1579622078.5805748, "gradients/classifier.weight": {"bins": [-0.1152126044034958, -0.11168204247951508, -0.10815148055553436, -0.10462091863155364, -0.10109035670757294, -0.09755979478359222, -0.09402924031019212, -0.0904986783862114, -0.08696811646223068, -0.08343755453824997, -0.07990699261426926, -0.07637643814086914, -0.07284587621688843, -0.06931531429290771, -0.065784752368927, -0.06225419044494629, -0.058723628520965576, -0.05519306659698486, -0.05166250467300415, -0.04813194274902344, -0.044601380825042725, -0.04107082635164261, -0.037540264427661896, -0.03400970250368118, -0.03047914057970047, -0.026948578655719757, -0.023418016731739044, -0.01988745480775833, -0.016356900334358215, -0.012826338410377502, -0.00929577648639679, -0.005765214562416077, -0.002234652638435364, 0.0012959092855453491, 0.004826471209526062, 0.008357033133506775, 0.011887595057487488, 0.0154181569814682, 0.018948718905448914, 0.022479280829429623, 0.02600984275341034, 0.02954038977622986, 0.03307095170021057, 0.03660151362419128, 0.040132075548172, 0.04366263747215271, 0.04719319939613342, 0.050723761320114136, 0.05425432324409485, 0.05778488516807556, 0.061315447092056274, 0.06484600901603699, 0.0683765709400177, 0.07190713286399841, 0.07543769478797913, 0.07896825671195984, 0.08249880373477936, 0.08602936565876007, 0.08955992758274078, 0.0930904895067215, 0.0966210514307022, 0.10015161335468292, 0.10368217527866364, 0.10721273720264436, 0.11074329912662506], "_type": "histogram", "values": [1, 1, 0, 0, 0, 0, 3, 5, 5, 3, 7, 10, 19, 15, 19, 35, 39, 51, 57, 70, 75, 112, 132, 143, 155, 199, 206, 269, 257, 299, 330, 333, 325, 333, 293, 284, 288, 265, 229, 239, 202, 194, 137, 112, 89, 78, 46, 49, 35, 22, 22, 17, 9, 6, 8, 2, 1, 3, 1, 1, 1, 2, 0, 1]}, "_step": 0, "gradients/classifier.bias": {"bins": [-0.13529202342033386, -0.13200686872005463, -0.12872172892093658, -0.12543657422065735, -0.12215142697095872, -0.11886627972126008, -0.11558113247156145, -0.1122959852218628, -0.10901083052158356, -0.10572568327188492, -0.10244053602218628, -0.09915538132190704, -0.095870241522789, -0.09258508682250977, -0.08929993957281113, -0.08601479232311249, -0.08272963762283325, -0.07944449782371521, -0.07615934312343597, -0.07287419587373734, -0.0695890486240387, -0.06630389392375946, -0.06301874667406082, -0.05973359942436218, -0.056448452174663544, -0.053163304924964905, -0.04987815022468567, -0.04659300297498703, -0.04330785572528839, -0.04002270847558975, -0.03673755377531051, -0.03345240652561188, -0.03016725927591324, -0.0268821120262146, -0.02359696477651596, -0.020311810076236725, -0.017026662826538086, -0.013741515576839449, -0.010456368327140808, -0.007171213626861572, -0.0038860738277435303, -0.0006009191274642944, 0.0026842355728149414, 0.005969375371932983, 0.00925453007221222, 0.01253966987133026, 0.015824824571609497, 0.019109979271888733, 0.022395119071006775, 0.02568027377128601, 0.028965413570404053, 0.03225056827068329, 0.035535722970962524, 0.038820862770080566, 0.0421060174703598, 0.04539117217063904, 0.04867631196975708, 0.05196146667003632, 0.05524660646915436, 0.058531761169433594, 0.06181691586971283, 0.06510205566883087, 0.06838721036911011, 0.07167235016822815, 0.07495750486850739], "_type": "histogram", "values": [1, 0, 0, 0, 0, 0, 0, 0, 0, 0, 0, 0, 0, 0, 0, 0, 0, 0, 0, 0, 0, 0, 0, 0, 0, 0, 0, 0, 0, 0, 0, 0, 0, 0, 0, 0, 0, 0, 0, 0, 0, 0, 0, 0, 0, 0, 1, 0, 0, 0, 0, 0, 0, 0, 1, 0, 0, 0, 0, 0, 0, 0, 0, 1]}, "val_acc": 0.7779669030732861}
