{
    "root": "/home/ubamba98/droughtwatch",
    "program": "<python with no main file>",
    "git": {
        "remote": "https://github.com/ubamba98/droughtwatch",
        "commit": "408b9281490300c85c432393af3f62d791048fcf"
    },
    "email": "ubamba98@gmail.com",
    "startedAt": "2020-01-20T19:25:59.322006",
    "host": "ccw-iclr",
    "username": "ubamba98",
    "executable": "/home/ubamba98/anaconda3/bin/python",
    "os": "Linux-4.9.0-11-amd64-x86_64-with-debian-9.11",
    "python": "3.7.3",
    "gpu": "Tesla T4",
    "gpu_count": 1,
    "cpu_count": 4,
    "cuda": "10.0.130",
    "args": [
        "-f",
        "/home/ubamba98/.local/share/jupyter/runtime/kernel-24d294e6-6e79-4baf-816f-44f684d7cf4e.json"
    ],
    "state": "running",
    "jobType": null,
    "mode": "run",
    "name": "efficentnet-b3-765",
    "project": "dr-challenge",
    "heartbeatAt": "2020-01-20T19:26:00.465424"
}
